{
  "points": [
    {
      "id": "5959-1",
      "name": "はとバス新宿営業所",
      "image": "https://image.xinu.ink/pic/data/5959/images/5959-1.jpg",
      "ep": "",
      "geo": [
        35.6915447,
        139.7012536
      ]
    },
    {
      "id": "5959-2",
      "name": "ローソン 新宿四丁目店",
      "image": "https://image.xinu.ink/pic/data/5959/images/5959-2.jpg",
      "ep": "",
      "geo": [
        35.68966,
        139.70445
      ]
    },
    {
      "id": "5959-3",
      "name": "新宿区内藤町自転車保管場所",
      "image": "https://image.xinu.ink/pic/data/5959/images/5959-3.jpg",
      "ep": "",
      "geo": [
        35.68922,
        139.70617
      ]
    },
    {
      "id": "5959-4",
      "name": "入園切符売り場（新宿門）",
      "image": "https://image.xinu.ink/pic/data/5959/images/5959-4.jpg",
      "ep": "",
      "geo": [
        35.688711,
        139.707248
      ]
    },
    {
      "id": "5959-5",
      "name": "上の池",
      "image": "https://image.xinu.ink/pic/data/5959/images/5959-5.jpg",
      "ep": "",
      "geo": [
        35.68537,
        139.70592
      ]
    },
    {
      "id": "5959-6",
      "name": "四阿",
      "image": "https://image.xinu.ink/pic/data/5959/images/5959-6.jpg",
      "ep": "",
      "geo": [
        35.68483,
        139.7082
      ]
    },
    {
      "id": "5959-7",
      "name": "松屋 新宿南口店",
      "image": "https://image.xinu.ink/pic/data/5959/images/5959-7.jpg",
      "ep": "",
      "geo": [
        35.69021,
        139.70218
      ]
    },
    {
      "id": "5959-8",
      "name": "こども広場",
      "image": "https://image.xinu.ink/pic/data/5959/images/5959-8.jpg",
      "ep": "",
      "geo": [
        35.68307,
        139.70852
      ]
    },
    {
      "id": "5959-9",
      "name": "上海飲茶猪八戒",
      "image": "https://image.xinu.ink/pic/data/5959/images/5959-9.jpg",
      "ep": "",
      "geo": [
        35.67857,
        139.71001
      ]
    },
    {
      "id": "5959-10",
      "name": "エクセルシオールカフェ 千駄ヶ谷駅前店",
      "image": "https://image.xinu.ink/pic/data/5959/images/5959-10.jpg",
      "ep": "",
      "geo": [
        35.68095,
        139.71104
      ]
    },
    {
      "id": "5959-11",
      "name": "八幡前架道橋付近",
      "image": "https://image.xinu.ink/pic/data/5959/images/5959-11.jpg",
      "ep": "",
      "geo": [
        35.6817825,
        139.7095592
      ]
    },
    {
      "id": "5959-12",
      "name": "金券ショップ ヨコハマチケットサービス新宿南口店 本店",
      "image": "https://image.xinu.ink/pic/data/5959/images/5959-12.jpg",
      "ep": "",
      "geo": [
        35.68942,
        139.70272
      ]
    },
    {
      "id": "5959-13",
      "name": "旧御凉亭（台湾閣）",
      "image": "https://image.xinu.ink/pic/data/5959/images/5959-13.jpg",
      "ep": "",
      "geo": [
        35.68475,
        139.7084
      ]
    },
    {
      "id": "5959-14",
      "name": "渋谷区役所千駄ヶ谷出張所",
      "image": "https://image.xinu.ink/pic/data/5959/images/5959-14.jpg",
      "ep": "",
      "geo": [
        35.6813,
        139.70549
      ]
    }
  ]
}